{
  "plants": [
    {
      "id": 2,
      "name": "Monstera Deliciosa",
      "category": "indoor",
      "price": "₹899",
      "image": "https://www.gardendesign.com/pictures/images/900x705Max/dream-team-s-portland-garden_6/beauty-star-calathea-calathea-ornata-pinstripe-calathea-proven-winners_17336.jpg",
      "description": "Swiss Cheese Plant with iconic split leaves",
      "details": "Monstera Deliciosa, known as the Swiss Cheese Plant, features stunning fenestrated leaves that develop natural holes as it matures. This tropical beauty thrives in bright, indirect light and well-draining soil. A statement piece that brings jungle vibes to any interior space.",
      "botanicalName": "Monstera Deliciosa",
      "careLevel": "Easy",
      "lightRequirement": "Bright, indirect light",
      "wateringFrequency": "Weekly",
      "humidity": "40-60%",
      "temperature": "18-27°C",
      "fertilizer": "Monthly during growing season",
      "toxicity": "Toxic to pets",
      "origin": "Central America",
      "maxHeight": "8 feet indoors",
      "potSize": "Large",
      "soilType": "Well-draining, peat-based mix",
      "propagation": "Stem cuttings, air layering",
      "commonProblems": "Yellowing leaves, root rot",
      "benefits": "Air purifying, fast growing",
      "seasonality": "Year-round",
      "repottingFrequency": "Every 2 years",
      "pruningNeeds": "Regular",
      "petFriendly": false,
      "airPurifying": true,
      "lowMaintenance": true,
      "flowering": false,
      "fragrant": false,
      "edible": false,
      "medicinal": false,
      "createdAt": "2024-01-15T10:30:00Z",
      "updatedAt": "2024-01-15T10:30:00Z"
    },
    {
      "id": 4,
      "name": "Air Purifying Red Anthurium Plant",
      "category": "indoor",
      "price": "₹749",
      "image": "https://www.rollingnature.com/cdn/shop/products/PLAMCEMSAR-W-Main.jpg?v=1576494071&width=1646",
      "description": "Bring your garden inside with elegant indoor plants & embossed ceramic pots from Rolling Nature. Rolling Nature's Aroez ceramic pot collection designs are inspired by Italian Sgraffito pottery",
      "details": "",
      "botanicalName": "",
      "careLevel": "Easy",
      "lightRequirement": "Medium to low light",
      "wateringFrequency": "Weekly",
      "humidity": "40-60%",
      "temperature": "18-24°C",
      "fertilizer": "Monthly during growing season",
      "toxicity": "Toxic to pets",
      "origin": "Tropical Americas",
      "maxHeight": "3 feet indoors",
      "potSize": "Medium",
      "soilType": "Well-draining potting mix",
      "propagation": "Division",
      "commonProblems": "Brown leaf tips, no flowers",
      "benefits": "Air purifying, flowering",
      "seasonality": "Year-round",
      "repottingFrequency": "Every 2 years",
      "pruningNeeds": "Regular deadheading",
      "petFriendly": false,
      "airPurifying": true,
      "lowMaintenance": true,
      "flowering": true,
      "fragrant": false,
      "edible": false,
      "medicinal": false,
      "createdAt": "2024-01-15T10:30:00Z",
      "updatedAt": "2025-07-27T12:58:59.831Z"
    },
    {
      "name": "White Customized Peperomia ",
      "category": "indoor",
      "price": "200",
      "image": "https://www.yourprint.in/new-admin-ajax.php?action=resize_outer_image&cfcache=all&url=med-s3/yP-mplace/Planters/YPB0CSFZPQ5R_1.jpg&resizeTo=600",
      "description": "Elevate your home and office decor with White Customized Peperomia Green Indoor Plants for Living Room",
      "details": "",
      "botanicalName": "",
      "careLevel": "Easy",
      "lightRequirement": "",
      "wateringFrequency": "",
      "humidity": "",
      "temperature": "",
      "fertilizer": "",
      "toxicity": "",
      "origin": "",
      "maxHeight": "",
      "potSize": "Medium",
      "soilType": "",
      "propagation": "",
      "commonProblems": "",
      "benefits": "",
      "seasonality": "Year-round",
      "repottingFrequency": "",
      "pruningNeeds": "",
      "petFriendly": true,
      "airPurifying": true,
      "lowMaintenance": true,
      "flowering": true,
      "fragrant": true,
      "edible": true,
      "medicinal": false,
      "id": 1753599577764,
      "createdAt": "2025-07-27T06:59:37.764Z",
      "updatedAt": "2025-07-27T06:59:37.764Z"
    },
    {
      "name": "Lemon Plant",
      "category": "outdoor",
      "price": "500",
      "image": "https://scontent.fblr24-3.fna.fbcdn.net/v/t1.6435-9/150835430_110278537750534_8151952810361478887_n.jpg?_nc_cat=102&ccb=1-7&_nc_sid=833d8c&_nc_ohc=lLny-uzIjCsQ7kNvwGCp_KX&_nc_oc=AdmiFNbQHsM3LGh7xjK2K6ofzUmzSvV8dVoMhzMKcgBMbysV47iDl8YuuKZ8wsvCGMU&_nc_zt=23&_nc_ht=scontent.fblr24-3.fna&_nc_gid=Fz-IC6rs7z5uzu-cnGA6CQ&oh=00_AfSNaPHlR9xrBikHmr0h5MaNeAB717c4naEBH3vccVi1YQ&oe=68AD8029",
      "description": "A Lemon plant grown from a seed will take nearly 5 years to start fruiting. A lemon tree can grow up to 20 feet tall depending on favorable environment factors. A lemon tree can produce up to 272 kilos of lemons in a year which is almost 4500 lemons per year",
      "details": "",
      "botanicalName": "Citrus limon",
      "careLevel": "Easy",
      "lightRequirement": "",
      "wateringFrequency": "",
      "humidity": "",
      "temperature": "",
      "fertilizer": "",
      "toxicity": "",
      "origin": "",
      "maxHeight": "",
      "potSize": "Medium",
      "soilType": "",
      "propagation": "",
      "commonProblems": "",
      "benefits": "",
      "seasonality": "Year-round",
      "repottingFrequency": "",
      "pruningNeeds": "",
      "petFriendly": true,
      "airPurifying": true,
      "lowMaintenance": true,
      "flowering": false,
      "fragrant": false,
      "edible": false,
      "medicinal": false,
      "id": 1753621227521,
      "createdAt": "2025-07-27T13:00:27.521Z",
      "updatedAt": "2025-07-27T13:00:27.521Z"
    }
  ],
  "categories": [
    {
      "id": "indoor",
      "name": "Indoor Plants",
      "description": "Perfect for home and office spaces",
      "icon": "🏠"
    },
    {
      "id": "outdoor",
      "name": "Outdoor Plants",
      "description": "Beautiful plants for gardens and patios",
      "icon": "🌳"
    },
    {
      "id": "flowering",
      "name": "Flowering Plants",
      "description": "Colorful blooms to brighten your space",
      "icon": "🌸"
    },
    {
      "id": "succulents",
      "name": "Succulents",
      "description": "Low-maintenance water-storing plants",
      "icon": "🌵"
    },
    {
      "id": "herbs",
      "name": "Herbs",
      "description": "Fresh herbs for cooking and wellness",
      "icon": "🌿"
    }
  ],
  "metadata": {
    "version": "1.0.0",
    "lastUpdated": "2025-07-27T13:01:26.415Z",
    "totalPlants": 4,
    "totalCategories": 5
  }
}